[{"phrase":"land managers","value":0.0},{"phrase":"greater yellowstone ecosystem","value":false},{"phrase":"natural resource managers","value":0.0},{"phrase":"resource managers","value":false},{"phrase":"model parameters","value":false},{"phrase":"south dakota","value":0.0},{"phrase":"wide range","value":false},{"phrase":"additional climate information","value":false},{"phrase":"regional assessment efforts","value":false},{"phrase":"species distribution models","value":0.0},{"phrase":"climate change projections","value":false},{"phrase":"future climate conditions","value":0.0},{"phrase":"resource management goals","value":false},{"phrase":"various climate changes","value":false},{"phrase":"native american leaders","value":false},{"phrase":"tribal representatives","value":false},{"phrase":"badlands national park","value":false},{"phrase":"species distributions","value":0.0},{"phrase":"conservation planning","value":0.0},{"phrase":"future climate change","value":false},{"phrase":"global climate models","value":0.0},{"phrase":"national park service","value":0.0},{"phrase":"critical information","value":false},{"phrase":"missouri river basin","value":false},{"phrase":"management decisions","value":false},{"phrase":"european settlement","value":false},{"phrase":"climatic conditions","value":false},{"phrase":"climate information","value":false},{"phrase":"adaptation planning","value":false},{"phrase":"biotic interactions","value":0.0},{"phrase":"ecosystem services","value":0.0},{"phrase":"time period ranges","value":false},{"phrase":"ecological impacts","value":0.0},{"phrase":"associated impacts","value":false},{"phrase":"climate scenarios","value":false},{"phrase":"climatic changes","value":false},{"phrase":"federal agencies","value":true},{"phrase":"uncertain future","value":0.0},{"phrase":"spatial patterns","value":false},{"phrase":"phenocam network","value":0.0},{"phrase":"climate changes","value":false},{"phrase":"climate warming","value":false},{"phrase":"plant responses","value":0.0},{"phrase":"northern plains","value":false},{"phrase":"water resources","value":false},{"phrase":"historic period","value":false},{"phrase":"rocky mountains","value":0.0},{"phrase":"land use change","value":false},{"phrase":"present project","value":false},{"phrase":"spatial scales","value":false},{"phrase":"national parks","value":false},{"phrase":"climate models","value":false},{"phrase":"climate zones","value":false},{"phrase":"broader range","value":0.0},{"phrase":"other species","value":0.0},{"phrase":"plant species","value":0.0},{"phrase":"north america","value":0.0},{"phrase":"many species","value":false},{"phrase":"case studies","value":false},{"phrase":"last century","value":false},{"phrase":"north dakota","value":false},{"phrase":"recent years","value":0.0},{"phrase":"great plains","value":0.0},{"phrase":"project team","value":false},{"phrase":"white pines","value":0.0},{"phrase":"org doi abs","value":false},{"phrase":"season sos","value":false},{"phrase":"gcm output","value":0.0},{"phrase":"landsat 8","value":false},{"phrase":"land managers","value":1.0},{"phrase":"greater yellowstone ecosystem","value":true},{"phrase":"natural resource managers","value":1.0},{"phrase":"resource managers","value":false},{"phrase":"model parameters","value":true},{"phrase":"south dakota","value":1.0},{"phrase":"wide range","value":true},{"phrase":"additional climate information","value":true},{"phrase":"regional assessment efforts","value":true},{"phrase":"species distribution models","value":1.0},{"phrase":"climate change projections","value":false},{"phrase":"future climate conditions","value":0.0},{"phrase":"resource management goals","value":false},{"phrase":"various climate changes","value":true},{"phrase":"native american leaders","value":true},{"phrase":"tribal representatives","value":false},{"phrase":"badlands national park","value":false},{"phrase":"species distributions","value":0.0},{"phrase":"conservation planning","value":0.0},{"phrase":"future climate change","value":false},{"phrase":"global climate models","value":1.0},{"phrase":"national park service","value":0.0},{"phrase":"critical information","value":true},{"phrase":"missouri river basin","value":false},{"phrase":"management decisions","value":true},{"phrase":"european settlement","value":true},{"phrase":"climatic conditions","value":true},{"phrase":"climate information","value":true},{"phrase":"adaptation planning","value":false},{"phrase":"biotic interactions","value":0.0},{"phrase":"ecosystem services","value":1.0},{"phrase":"time period ranges","value":false},{"phrase":"ecological impacts","value":0.0},{"phrase":"associated impacts","value":false},{"phrase":"climate scenarios","value":false},{"phrase":"climatic changes","value":true},{"phrase":"federal agencies","value":false},{"phrase":"uncertain future","value":1.0},{"phrase":"spatial patterns","value":false},{"phrase":"phenocam network","value":0.0},{"phrase":"climate changes","value":true},{"phrase":"climate warming","value":true},{"phrase":"plant responses","value":0.0},{"phrase":"northern plains","value":false},{"phrase":"water resources","value":true},{"phrase":"historic period","value":false},{"phrase":"rocky mountains","value":0.0},{"phrase":"land use change","value":true},{"phrase":"present project","value":false},{"phrase":"spatial scales","value":true},{"phrase":"national parks","value":true},{"phrase":"climate models","value":true},{"phrase":"climate zones","value":false},{"phrase":"broader range","value":0.0},{"phrase":"other species","value":0.0},{"phrase":"plant species","value":0.0},{"phrase":"north america","value":0.0},{"phrase":"many species","value":false},{"phrase":"case studies","value":false},{"phrase":"last century","value":false},{"phrase":"north dakota","value":false},{"phrase":"recent years","value":0.0},{"phrase":"great plains","value":1.0},{"phrase":"project team","value":false},{"phrase":"white pines","value":0.0},{"phrase":"org doi abs","value":true},{"phrase":"season sos","value":true},{"phrase":"gcm output","value":0.0},{"phrase":"landsat 8","value":true},{"phrase":"land managers","value":3.0},{"phrase":"greater yellowstone ecosystem","value":true},{"phrase":"natural resource managers","value":3.0},{"phrase":"resource managers","value":true},{"phrase":"model parameters","value":false},{"phrase":"south dakota","value":1.0},{"phrase":"wide range","value":false},{"phrase":"additional climate information","value":true},{"phrase":"regional assessment efforts","value":true},{"phrase":"species distribution models","value":2.0},{"phrase":"climate change projections","value":true},{"phrase":"future climate conditions","value":2.0},{"phrase":"resource management goals","value":false},{"phrase":"various climate changes","value":true},{"phrase":"native american leaders","value":true},{"phrase":"tribal representatives","value":false},{"phrase":"badlands national park","value":false},{"phrase":"species distributions","value":2.0},{"phrase":"conservation planning","value":2.0},{"phrase":"future climate change","value":true},{"phrase":"global climate models","value":0.0},{"phrase":"national park service","value":1.0},{"phrase":"critical information","value":false},{"phrase":"missouri river basin","value":true},{"phrase":"management decisions","value":true},{"phrase":"european settlement","value":false},{"phrase":"climatic conditions","value":true},{"phrase":"climate information","value":true},{"phrase":"adaptation planning","value":true},{"phrase":"biotic interactions","value":2.0},{"phrase":"ecosystem services","value":2.0},{"phrase":"time period ranges","value":false},{"phrase":"ecological impacts","value":0.0},{"phrase":"associated impacts","value":false},{"phrase":"climate scenarios","value":false},{"phrase":"climatic changes","value":true},{"phrase":"federal agencies","value":true},{"phrase":"uncertain future","value":2.0},{"phrase":"spatial patterns","value":false},{"phrase":"phenocam network","value":0.0},{"phrase":"climate changes","value":true},{"phrase":"climate warming","value":true},{"phrase":"plant responses","value":2.0},{"phrase":"northern plains","value":true},{"phrase":"water resources","value":false},{"phrase":"historic period","value":false},{"phrase":"rocky mountains","value":0.0},{"phrase":"land use change","value":false},{"phrase":"present project","value":false},{"phrase":"spatial scales","value":false},{"phrase":"national parks","value":false},{"phrase":"climate models","value":true},{"phrase":"climate zones","value":true},{"phrase":"broader range","value":2.0},{"phrase":"other species","value":2.0},{"phrase":"plant species","value":0.0},{"phrase":"north america","value":0.0},{"phrase":"many species","value":true},{"phrase":"case studies","value":true},{"phrase":"last century","value":true},{"phrase":"north dakota","value":false},{"phrase":"recent years","value":0.0},{"phrase":"great plains","value":0.0},{"phrase":"project team","value":false},{"phrase":"white pines","value":2.0},{"phrase":"org doi abs","value":true},{"phrase":"season sos","value":false},{"phrase":"gcm output","value":0.0},{"phrase":"landsat 8","value":false},{"phrase":"land managers","value":0.0},{"phrase":"greater yellowstone ecosystem","value":true},{"phrase":"natural resource managers","value":1.0},{"phrase":"resource managers","value":true},{"phrase":"model parameters","value":false},{"phrase":"south dakota","value":1.0},{"phrase":"wide range","value":false},{"phrase":"additional climate information","value":false},{"phrase":"regional assessment efforts","value":false},{"phrase":"species distribution models","value":1.0},{"phrase":"climate change projections","value":true},{"phrase":"future climate conditions","value":1.0},{"phrase":"resource management goals","value":false},{"phrase":"various climate changes","value":false},{"phrase":"native american leaders","value":false},{"phrase":"tribal representatives","value":false},{"phrase":"badlands national park","value":false},{"phrase":"species distributions","value":0.0},{"phrase":"conservation planning","value":0.0},{"phrase":"future climate change","value":false},{"phrase":"global climate models","value":2.0},{"phrase":"national park service","value":0.0},{"phrase":"critical information","value":false},{"phrase":"missouri river basin","value":true},{"phrase":"management decisions","value":false},{"phrase":"european settlement","value":true},{"phrase":"climatic conditions","value":false},{"phrase":"climate information","value":false},{"phrase":"adaptation planning","value":false},{"phrase":"biotic interactions","value":1.0},{"phrase":"ecosystem services","value":2.0},{"phrase":"time period ranges","value":true},{"phrase":"ecological impacts","value":2.0},{"phrase":"associated impacts","value":true},{"phrase":"climate scenarios","value":false},{"phrase":"climatic changes","value":false},{"phrase":"federal agencies","value":true},{"phrase":"uncertain future","value":0.0},{"phrase":"spatial patterns","value":true},{"phrase":"phenocam network","value":1.0},{"phrase":"climate changes","value":false},{"phrase":"climate warming","value":true},{"phrase":"plant responses","value":0.0},{"phrase":"northern plains","value":false},{"phrase":"water resources","value":true},{"phrase":"historic period","value":true},{"phrase":"rocky mountains","value":2.0},{"phrase":"land use change","value":true},{"phrase":"present project","value":false},{"phrase":"spatial scales","value":false},{"phrase":"national parks","value":false},{"phrase":"climate models","value":true},{"phrase":"climate zones","value":false},{"phrase":"broader range","value":0.0},{"phrase":"other species","value":0.0},{"phrase":"plant species","value":1.0},{"phrase":"north america","value":0.0},{"phrase":"many species","value":false},{"phrase":"case studies","value":true},{"phrase":"last century","value":false},{"phrase":"north dakota","value":false},{"phrase":"recent years","value":1.0},{"phrase":"great plains","value":2.0},{"phrase":"project team","value":true},{"phrase":"white pines","value":0.0},{"phrase":"org doi abs","value":true},{"phrase":"season sos","value":false},{"phrase":"gcm output","value":2.0},{"phrase":"landsat 8","value":false},{"phrase":"land managers","value":1.0},{"phrase":"greater yellowstone ecosystem","value":false},{"phrase":"natural resource managers","value":0.0},{"phrase":"resource managers","value":true},{"phrase":"model parameters","value":true},{"phrase":"south dakota","value":2.0},{"phrase":"wide range","value":true},{"phrase":"additional climate information","value":false},{"phrase":"regional assessment efforts","value":false},{"phrase":"species distribution models","value":0.0},{"phrase":"climate change projections","value":false},{"phrase":"future climate conditions","value":0.0},{"phrase":"resource management goals","value":false},{"phrase":"various climate changes","value":false},{"phrase":"native american leaders","value":false},{"phrase":"tribal representatives","value":true},{"phrase":"badlands national park","value":true},{"phrase":"species distributions","value":0.0},{"phrase":"conservation planning","value":0.0},{"phrase":"future climate change","value":true},{"phrase":"global climate models","value":0.0},{"phrase":"national park service","value":0.0},{"phrase":"critical information","value":false},{"phrase":"missouri river basin","value":false},{"phrase":"management decisions","value":false},{"phrase":"european settlement","value":false},{"phrase":"climatic conditions","value":false},{"phrase":"climate information","value":false},{"phrase":"adaptation planning","value":false},{"phrase":"biotic interactions","value":0.0},{"phrase":"ecosystem services","value":0.0},{"phrase":"time period ranges","value":false},{"phrase":"ecological impacts","value":1.0},{"phrase":"associated impacts","value":true},{"phrase":"climate scenarios","value":true},{"phrase":"climatic changes","value":false},{"phrase":"federal agencies","value":false},{"phrase":"uncertain future","value":1.0},{"phrase":"spatial patterns","value":true},{"phrase":"phenocam network","value":0.0},{"phrase":"climate changes","value":false},{"phrase":"climate warming","value":false},{"phrase":"plant responses","value":0.0},{"phrase":"northern plains","value":true},{"phrase":"water resources","value":true},{"phrase":"historic period","value":false},{"phrase":"rocky mountains","value":0.0},{"phrase":"land use change","value":true},{"phrase":"present project","value":false},{"phrase":"spatial scales","value":false},{"phrase":"national parks","value":false},{"phrase":"climate models","value":false},{"phrase":"climate zones","value":false},{"phrase":"broader range","value":0.0},{"phrase":"other species","value":1.0},{"phrase":"plant species","value":1.0},{"phrase":"north america","value":1.0},{"phrase":"many species","value":true},{"phrase":"case studies","value":false},{"phrase":"last century","value":false},{"phrase":"north dakota","value":true},{"phrase":"recent years","value":2.0},{"phrase":"great plains","value":0.0},{"phrase":"project team","value":false},{"phrase":"white pines","value":0.0},{"phrase":"org doi abs","value":false},{"phrase":"season sos","value":false},{"phrase":"gcm output","value":0.0},{"phrase":"landsat 8","value":false},{"phrase":"land managers","value":0.0},{"phrase":"greater yellowstone ecosystem","value":false},{"phrase":"natural resource managers","value":0.0},{"phrase":"resource managers","value":false},{"phrase":"model parameters","value":false},{"phrase":"south dakota","value":0.0},{"phrase":"wide range","value":true},{"phrase":"additional climate information","value":false},{"phrase":"regional assessment efforts","value":false},{"phrase":"species distribution models","value":0.0},{"phrase":"climate change projections","value":false},{"phrase":"future climate conditions","value":0.0},{"phrase":"resource management goals","value":false},{"phrase":"various climate changes","value":false},{"phrase":"native american leaders","value":false},{"phrase":"tribal representatives","value":false},{"phrase":"badlands national park","value":false},{"phrase":"species distributions","value":0.0},{"phrase":"conservation planning","value":0.0},{"phrase":"future climate change","value":false},{"phrase":"global climate models","value":0.0},{"phrase":"national park service","value":0.0},{"phrase":"critical information","value":true},{"phrase":"missouri river basin","value":false},{"phrase":"management decisions","value":true},{"phrase":"european settlement","value":false},{"phrase":"climatic conditions","value":false},{"phrase":"climate information","value":false},{"phrase":"adaptation planning","value":false},{"phrase":"biotic interactions","value":0.0},{"phrase":"ecosystem services","value":0.0},{"phrase":"time period ranges","value":false},{"phrase":"ecological impacts","value":0.0},{"phrase":"associated impacts","value":false},{"phrase":"climate scenarios","value":false},{"phrase":"climatic changes","value":false},{"phrase":"federal agencies","value":false},{"phrase":"uncertain future","value":0.0},{"phrase":"spatial patterns","value":true},{"phrase":"phenocam network","value":2.0},{"phrase":"climate changes","value":false},{"phrase":"climate warming","value":false},{"phrase":"plant responses","value":0.0},{"phrase":"northern plains","value":false},{"phrase":"water resources","value":false},{"phrase":"historic period","value":false},{"phrase":"rocky mountains","value":0.0},{"phrase":"land use change","value":false},{"phrase":"present project","value":false},{"phrase":"spatial scales","value":true},{"phrase":"national parks","value":false},{"phrase":"climate models","value":false},{"phrase":"climate zones","value":true},{"phrase":"broader range","value":0.0},{"phrase":"other species","value":0.0},{"phrase":"plant species","value":2.0},{"phrase":"north america","value":2.0},{"phrase":"many species","value":false},{"phrase":"case studies","value":false},{"phrase":"last century","value":false},{"phrase":"north dakota","value":false},{"phrase":"recent years","value":0.0},{"phrase":"great plains","value":0.0},{"phrase":"project team","value":false},{"phrase":"white pines","value":0.0},{"phrase":"org doi abs","value":false},{"phrase":"season sos","value":true},{"phrase":"gcm output","value":0.0},{"phrase":"landsat 8","value":true},{"phrase":"land managers","value":0.0},{"phrase":"greater yellowstone ecosystem","value":false},{"phrase":"natural resource managers","value":4.0},{"phrase":"resource managers","value":true},{"phrase":"model parameters","value":true},{"phrase":"south dakota","value":1.0},{"phrase":"wide range","value":true},{"phrase":"additional climate information","value":false},{"phrase":"regional assessment efforts","value":false},{"phrase":"species distribution models","value":2.0},{"phrase":"climate change projections","value":false},{"phrase":"future climate conditions","value":0.0},{"phrase":"resource management goals","value":true},{"phrase":"various climate changes","value":false},{"phrase":"native american leaders","value":false},{"phrase":"tribal representatives","value":true},{"phrase":"badlands national park","value":true},{"phrase":"species distributions","value":0.0},{"phrase":"conservation planning","value":0.0},{"phrase":"future climate change","value":false},{"phrase":"global climate models","value":0.0},{"phrase":"national park service","value":1.0},{"phrase":"critical information","value":false},{"phrase":"missouri river basin","value":false},{"phrase":"management decisions","value":true},{"phrase":"european settlement","value":false},{"phrase":"climatic conditions","value":true},{"phrase":"climate information","value":true},{"phrase":"adaptation planning","value":true},{"phrase":"biotic interactions","value":0.0},{"phrase":"ecosystem services","value":0.0},{"phrase":"time period ranges","value":true},{"phrase":"ecological impacts","value":0.0},{"phrase":"associated impacts","value":false},{"phrase":"climate scenarios","value":true},{"phrase":"climatic changes","value":false},{"phrase":"federal agencies","value":false},{"phrase":"uncertain future","value":1.0},{"phrase":"spatial patterns","value":false},{"phrase":"phenocam network","value":0.0},{"phrase":"climate changes","value":false},{"phrase":"climate warming","value":false},{"phrase":"plant responses","value":0.0},{"phrase":"northern plains","value":false},{"phrase":"water resources","value":false},{"phrase":"historic period","value":true},{"phrase":"rocky mountains","value":1.0},{"phrase":"land use change","value":true},{"phrase":"present project","value":true},{"phrase":"spatial scales","value":false},{"phrase":"national parks","value":false},{"phrase":"climate models","value":true},{"phrase":"climate zones","value":false},{"phrase":"broader range","value":0.0},{"phrase":"other species","value":1.0},{"phrase":"plant species","value":0.0},{"phrase":"north america","value":2.0},{"phrase":"many species","value":false},{"phrase":"case studies","value":false},{"phrase":"last century","value":false},{"phrase":"north dakota","value":true},{"phrase":"recent years","value":0.0},{"phrase":"great plains","value":2.0},{"phrase":"project team","value":true},{"phrase":"white pines","value":0.0},{"phrase":"org doi abs","value":false},{"phrase":"season sos","value":false},{"phrase":"gcm output","value":0.0},{"phrase":"landsat 8","value":false},{"phrase":"land managers","value":0.0},{"phrase":"greater yellowstone ecosystem","value":false},{"phrase":"natural resource managers","value":1.0},{"phrase":"resource managers","value":true},{"phrase":"model parameters","value":false},{"phrase":"south dakota","value":1.0},{"phrase":"wide range","value":false},{"phrase":"additional climate information","value":false},{"phrase":"regional assessment efforts","value":false},{"phrase":"species distribution models","value":0.0},{"phrase":"climate change projections","value":false},{"phrase":"future climate conditions","value":0.0},{"phrase":"resource management goals","value":true},{"phrase":"various climate changes","value":false},{"phrase":"native american leaders","value":false},{"phrase":"tribal representatives","value":false},{"phrase":"badlands national park","value":false},{"phrase":"species distributions","value":0.0},{"phrase":"conservation planning","value":0.0},{"phrase":"future climate change","value":false},{"phrase":"global climate models","value":0.0},{"phrase":"national park service","value":2.0},{"phrase":"critical information","value":false},{"phrase":"missouri river basin","value":false},{"phrase":"management decisions","value":false},{"phrase":"european settlement","value":false},{"phrase":"climatic conditions","value":false},{"phrase":"climate information","value":false},{"phrase":"adaptation planning","value":false},{"phrase":"biotic interactions","value":0.0},{"phrase":"ecosystem services","value":0.0},{"phrase":"time period ranges","value":false},{"phrase":"ecological impacts","value":0.0},{"phrase":"associated impacts","value":false},{"phrase":"climate scenarios","value":false},{"phrase":"climatic changes","value":false},{"phrase":"federal agencies","value":false},{"phrase":"uncertain future","value":0.0},{"phrase":"spatial patterns","value":false},{"phrase":"phenocam network","value":0.0},{"phrase":"climate changes","value":false},{"phrase":"climate warming","value":false},{"phrase":"plant responses","value":0.0},{"phrase":"northern plains","value":false},{"phrase":"water resources","value":false},{"phrase":"historic period","value":false},{"phrase":"rocky mountains","value":0.0},{"phrase":"land use change","value":false},{"phrase":"present project","value":true},{"phrase":"spatial scales","value":false},{"phrase":"national parks","value":true},{"phrase":"climate models","value":false},{"phrase":"climate zones","value":false},{"phrase":"broader range","value":0.0},{"phrase":"other species","value":0.0},{"phrase":"plant species","value":0.0},{"phrase":"north america","value":1.0},{"phrase":"many species","value":false},{"phrase":"case studies","value":false},{"phrase":"last century","value":true},{"phrase":"north dakota","value":false},{"phrase":"recent years","value":0.0},{"phrase":"great plains","value":0.0},{"phrase":"project team","value":true},{"phrase":"white pines","value":0.0},{"phrase":"org doi abs","value":false},{"phrase":"season sos","value":false},{"phrase":"gcm output","value":0.0},{"phrase":"landsat 8","value":false}]